compote/__init__.py
compote/py.typed
compote-0.0.2.dist-info/METADATA
compote-0.0.2.dist-info/WHEEL
compote-0.0.2.dist-info/licenses/LICENSE
compote-0.0.2.dist-info/RECORD
