Metadata-Version: 2.4
Name: compote
Version: 0.0.2
Summary: A configuration utility for Python progams
Author-email: Peter Doherty <pdoherty@protonmail.com>
License-File: LICENSE
Requires-Python: >=3.13
